mk8dx_table_reader/__init__.py
mk8dx_table_reader/error_handling.py
mk8dx_table_reader/fullreader.py
mk8dx_table_reader/kerasUseModelScores.py
mk8dx_table_reader/table_img_generation.py
mk8dx_table_reader/yoloUseModelPlayers.py
mk8dx_table_reader/yoloUseModelTable.py
mk8dx_table_reader/models/__init__.py
mk8dx_table_reader/models/number_recognition_model.onnx
mk8dx_table_reader-0.5.5.dist-info/licenses/LICENSE.md
mk8dx_table_reader-0.5.5.dist-info/METADATA
mk8dx_table_reader-0.5.5.dist-info/WHEEL
mk8dx_table_reader-0.5.5.dist-info/top_level.txt
mk8dx_table_reader-0.5.5.dist-info/RECORD
