Metadata-Version: 2.4
Name: mk8dx_table_reader
Version: 0.5.5
Summary: A package to extract player names and scores from MK8DX tables using YOLO and EasyOCR.
Home-page: https://github.com/PrizeWhipser/shortcat.tips
Author: Julien ABADIE
Author-email: julien.abadie@etu.uca.fr
Classifier: Programming Language :: Python :: 3
Requires-Python: >=3.11.11
License-File: LICENSE.md
Requires-Dist: pillow
Requires-Dist: opencv-python
Requires-Dist: easyocr
Requires-Dist: numpy
Requires-Dist: setuptools
Requires-Dist: onnxruntime
Dynamic: author
Dynamic: author-email
Dynamic: classifier
Dynamic: description
Dynamic: description-content-type
Dynamic: home-page
Dynamic: license-file
Dynamic: requires-dist
Dynamic: requires-python
Dynamic: summary
